CHANGELOG.rst
fru/__init__.py
fru/__main__.py
fru/console.py
fru/exceptions.py
fru/fru_format.py
fru/shared.py
fru/toml_format.py
fru-4.1.0.dist-info/LICENSE.txt
fru-4.1.0.dist-info/METADATA
fru-4.1.0.dist-info/WHEEL
fru-4.1.0.dist-info/entry_points.txt
fru-4.1.0.dist-info/RECORD
