Metadata-Version: 2.1
Name: fru
Version: 4.1.0
Summary: Read and write binary FRU files
Home-page: https://github.com/genotrance/fru-tool/
License: MIT
Keywords: fru,ipmi
Author: Kurt McKee
Author-email: contactme@kurtmckee.org
Requires-Python: >=3.8
Classifier: Development Status :: 5 - Production/Stable
Classifier: Intended Audience :: Customer Service
Classifier: Intended Audience :: Developers
Classifier: Intended Audience :: Manufacturing
Classifier: License :: OSI Approved :: MIT License
Classifier: Natural Language :: English
Classifier: Operating System :: OS Independent
Classifier: Programming Language :: Python :: 3
Classifier: Programming Language :: Python :: 3.8
Classifier: Programming Language :: Python :: 3.9
Classifier: Programming Language :: Python :: 3.10
Classifier: Programming Language :: Python :: 3.11
Classifier: Programming Language :: Python :: 3.12
Classifier: Topic :: System :: Hardware
Classifier: Topic :: Utilities
Requires-Dist: click (>=8.0.0,<9.0.0)
Requires-Dist: tomli (>=2.0.1,<3.0.0) ; python_version < "3.11"
Project-URL: Repository, https://github.com/genotrance/fru-tool/
